{
    "todos": [],
    "notes": [],
    "habits": [
        {
            "name": "running",
            "streak": 1,
            "last_done": "2025-11-26"
        },
        {
            "name": "cycling",
            "streak": 0,
            "last_done": null
        }
    ],
    "attendance": [
        {
            "subject": "phy",
            "total_classes": 100,
            "classes_done": 40,
            "attended_classes": 35,
            "attendance_percentage": 87.5,
            "max_skips": 10
        }
    ],
    "budget": {
        "total": 0,
        "remaining": 0,
        "expenses": []
    },
    "documents": []
}